lightweight_gan/__init__.py
lightweight_gan/cli.py
lightweight_gan/diff_augment.py
lightweight_gan/diff_augment_test.py
lightweight_gan/lightweight_gan.py
lightweight_gan/version.py
lightweight_gan-1.2.1.dist-info/LICENSE
lightweight_gan-1.2.1.dist-info/METADATA
lightweight_gan-1.2.1.dist-info/WHEEL
lightweight_gan-1.2.1.dist-info/entry_points.txt
lightweight_gan-1.2.1.dist-info/top_level.txt
lightweight_gan-1.2.1.dist-info/RECORD
