Metadata-Version: 2.2
Name: lightweight-gan
Version: 1.2.1
Summary: Lightweight GAN
Home-page: https://github.com/lucidrains/lightweight-gan
Author: Phil Wang
Author-email: lucidrains@gmail.com
License: MIT
Keywords: artificial intelligence,deep learning,generative adversarial networks
Classifier: Development Status :: 4 - Beta
Classifier: Intended Audience :: Developers
Classifier: Topic :: Scientific/Engineering :: Artificial Intelligence
Classifier: License :: OSI Approved :: MIT License
Classifier: Programming Language :: Python :: 3.6
License-File: LICENSE
Requires-Dist: adabelief-pytorch
Requires-Dist: einops>=0.8.0
Requires-Dist: fire
Requires-Dist: kornia>=0.5.4
Requires-Dist: numpy
Requires-Dist: pillow
Requires-Dist: retry
Requires-Dist: torch>=2.2
Requires-Dist: torchvision
Requires-Dist: tqdm
Dynamic: author
Dynamic: author-email
Dynamic: classifier
Dynamic: home-page
Dynamic: keywords
Dynamic: license
Dynamic: requires-dist
Dynamic: summary
